lawyerup/__init__.py
lawyerup/core.py
lawyerup/template-generic.txt
lawyerup/template-GPR.txt
lawyerup/template-GRR.txt
lawyerup-0.1.5.dist-info/DESCRIPTION.rst
lawyerup-0.1.5.dist-info/entry_points.txt
lawyerup-0.1.5.dist-info/METADATA
lawyerup-0.1.5.dist-info/metadata.json
lawyerup-0.1.5.dist-info/pbr.json
lawyerup-0.1.5.dist-info/RECORD
lawyerup-0.1.5.dist-info/top_level.txt
lawyerup-0.1.5.dist-info/WHEEL
