Metadata-Version: 2.0
Name: lawyerup
Version: 0.1.5
Summary: LawyerUp adds license headers to your code
Home-page: https://github.com/redjack/lawyerup
Author: Andy Freeland
Author-email: andy.freeland@redjack.com
License: UNKNOWN
Keywords: lawyerup
Platform: UNKNOWN
Classifier: Development Status :: 2 - Pre-Alpha
Classifier: Intended Audience :: Developers
Classifier: Natural Language :: English
Classifier: Programming Language :: Python :: 2
Classifier: Programming Language :: Python :: 2.6
Classifier: Programming Language :: Python :: 2.7
Classifier: Programming Language :: Python :: 3
Classifier: Programming Language :: Python :: 3.3
Classifier: Programming Language :: Python :: 3.4
Classifier: Programming Language :: Python :: Implementation :: PyPy
Requires-Dist: argparse; python_version=="2.6"
